texttoolz/__init__.py
texttoolz/main.py
texttoolz-0.1.0.dist-info/METADATA
texttoolz-0.1.0.dist-info/WHEEL
texttoolz-0.1.0.dist-info/top_level.txt
texttoolz-0.1.0.dist-info/RECORD
